property_utils/__init__.py
property_utils/py.typed
property_utils/constants/__init__.py
property_utils/constants/constants.py
property_utils/exceptions/__init__.py
property_utils/exceptions/base.py
property_utils/exceptions/properties/__init__.py
property_utils/exceptions/properties/property.py
property_utils/exceptions/units/__init__.py
property_utils/exceptions/units/converter_types.py
property_utils/exceptions/units/descriptors.py
property_utils/properties/__init__.py
property_utils/properties/property.py
property_utils/properties/validated_property.py
property_utils/units/__init__.py
property_utils/units/aliases.py
property_utils/units/converter_types.py
property_utils/units/converters.py
property_utils/units/descriptors.py
property_utils/units/units.py
property_utils-0.3.1.dist-info/LICENSE
property_utils-0.3.1.dist-info/METADATA
property_utils-0.3.1.dist-info/WHEEL
property_utils-0.3.1.dist-info/top_level.txt
property_utils-0.3.1.dist-info/RECORD
