Metadata-Version: 2.1
Name: property-utils
Version: 0.3.1
Summary: Utilities for programming that involves physical properties
Author-email: Maximos Nikiforakis <nikiforos@live.co.uk>
License: MIT
Project-URL: Homepage, https://github.com/Maxcode123/property-utils
Project-URL: Issues, https://github.com/Maxcode123/property-utils/issues
Keywords: physical properties,properties
Classifier: Programming Language :: Python
Classifier: Programming Language :: Python :: 3
Classifier: Programming Language :: Python :: 3.8
Classifier: Programming Language :: Python :: 3.9
Classifier: Programming Language :: Python :: 3.10
Classifier: Programming Language :: Python :: 3.11
Classifier: Programming Language :: Python :: 3.12
Classifier: Intended Audience :: Science/Research
Classifier: Natural Language :: English
Classifier: License :: OSI Approved :: MIT License
Classifier: Operating System :: POSIX :: Linux
Classifier: Operating System :: Microsoft :: Windows
Classifier: Operating System :: MacOS
Classifier: Topic :: Scientific/Engineering :: Chemistry
Classifier: Topic :: Scientific/Engineering :: Physics
Requires-Python: >=3.8
License-File: LICENSE
Requires-Dist: typing-extensions
Provides-Extra: dev
Requires-Dist: unittest-extensions ; extra == 'dev'
Requires-Dist: black ; extra == 'dev'
